setup.py
distributions_tl/Binomial.py
distributions_tl/Distribution.py
distributions_tl/Gaussian.py
distributions_tl/__init__.py
distributions_tl.egg-info/PKG-INFO
distributions_tl.egg-info/SOURCES.txt
distributions_tl.egg-info/dependency_links.txt
distributions_tl.egg-info/not-zip-safe
distributions_tl.egg-info/top_level.txt