Metadata-Version: 1.0
Name: distributions-tl
Version: 0.1
Summary: Gaussian and Binomial Distributions
Home-page: UNKNOWN
Author: Teanlouise
Author-email: UNKNOWN
License: UNKNOWN
Platform: UNKNOWN
